Workbook

Sheet Instructions
B2: HR Dashboard Data Pack — Padakhep Manabik Unnayan Kendra
B3: Prepared as a ready-to-use data source for building an HR dashboard (PivotTables / Charts / Power BI).
B5: What's inside
B6: Employee_Master | C6: One row per employee — the core table. Feeds headcount, demographics, tenure, salary, department/branch splits.
B7: Recruitment | C7: Vacancy-to-hire tracking — time-to-fill, applicant funnel, source of hire.
B8: Attrition | C8: Separated employees — exit type, reason, tenure at exit. Feeds turnover rate.
B9: Training | C9: Training records per employee — hours, cost, category. Feeds training coverage & spend.
B10: Leave | C10: Leave entitlement/taken/balance by employee and type.
B11: Dept_Payroll_Summary | C11: Formula-driven roll-up by department (headcount, avg salary, gender split) — auto-updates from Employee_Master.
B12: Dashboard_KPIs | C12: Headline KPIs + breakdown tables + charts, all formula-driven from the sheets above. Copy this sheet's tables into your dashboard tool, or build directly on it.
B14: IMPORTANT — this is SAMPLE data
C15: All employee names, IDs, salaries and dates in this workbook are FICTIONAL placeholders generated to match Padakhep's known scale (700+ offices, 4,500+ employees, 8 divisions, per padakhep.org) and typical NGO/MFI department structure. Real HRIS/payroll export data was NOT available to me — please replace the sample rows with your actual employee records.
B16: How to use
B17: 1. | C17: Export your live data from your HRIS/payroll system (or ask HR/Admin for the register) into the same column structure as each sheet below.
B18: 2. | C18: Paste your real records into Employee_Master, Recruitment, Attrition, Training and Leave, replacing the sample rows (keep the header row).
B19: 3. | C19: Dept_Payroll_Summary and Dashboard_KPIs will recalculate automatically — they reference the tables by name, not hardcoded values.
B20: 4. | C20: Cells shaded yellow are the ones meant to be typed/edited; formula cells are left un-shaded — do not overwrite them.
B21: 5. | C21: Build your dashboard (charts/slicers) from Dashboard_KPIs, or load Employee_Master into a PivotTable for deeper cuts.
B23: Source: company overview, scale figures and division names taken from https://www.padakhep.org/ (accessed Sept 2026).

Sheet Dashboard_KPIs
B2: HR Dashboard — Key Metrics
B3: Padakhep Manabik Unnayan Kendra | All figures auto-calculate from Employee_Master / Recruitment / Attrition / Training
B6: Total Active Headcount | E6: Total Employees (incl. separated) | H6: % Female | K6: Average Age (yrs)
B7: =COUNTIFS(Employee_Master[Employment Status],"Active") -> 143 | E7: =COUNTA(Employee_Master[EmpID]) -> 160 | H7: =COUNTIFS(Employee_Master[Employment Status],"Active",Employee_Master[Gender],"Female")/COUNTIFS(Employee_Master[Employment Status],"Active") -> 0.35664336 | K7: =AVERAGEIFS(Employee_Master[Age],Employee_Master[Employment Status],"Active") -> 40.48951
B10: Average Tenure (yrs) | E10: New Hires (last 12 months) | H10: Separations (last 12 months) | K10: Annualized Turnover Rate
B11: =AVERAGEIFS(Employee_Master[Tenure (Years)],Employee_Master[Employment Status],"Active") -> 8.8741259 | E11: =COUNTIFS(Employee_Master[Joining Date],">="&EDATE(TODAY(),-12)) -> 12 | H11: =COUNTIFS(Attrition[Exit Date],">="&EDATE(TODAY(),-12)) -> 4 | K11: =IFERROR(COUNTIFS(Attrition[Exit Date],">="&EDATE(TODAY(),-12))/COUNTIFS(Employee_Master[Employment Status],"Active"),0) -> 0.027972028
B14: Open Positions (Recruitment) | E14: Avg. Days to Fill a Vacancy | H14: Training Sessions (this year) | K14: Total Training Spend (BDT)
B15: =COUNTIF(Recruitment[Position Filled Date],"Open") -> 5 | E15: =IFERROR(AVERAGE(Recruitment[Days to Fill]),0) -> 42.466667 | H15: =COUNTA(Training[EmpID]) -> 70 | K15: =SUM(Training[Cost (BDT)]) -> 462035
B20: Active Headcount by Department | F20: Active Headcount by Gender | I20: Headcount by Employment Type | L20: Active Headcount by Region
B21: Department | C21: Headcount | F21: Gender | G21: Headcount | I21: Employment Type | J21: Headcount | L21: Region | M21: Headcount
B22: =Dept_Payroll_Summary!B6 -> Agriculture & Climate Adaptation | C22: =Dept_Payroll_Summary!C6 -> 2 | F22: Male | G22: =COUNTIFS(Employee_Master[Employment Status],"Active",Employee_Master[Gender],"Male") -> 92 | I22: Permanent | J22: =COUNTIFS(Employee_Master[Employment Status],"Active",Employee_Master[Employment Type],"Permanent") -> 93 | L22: Barishal | M22: =COUNTIFS(Employee_Master[Employment Status],"Active",Employee_Master[Region/Division],"Barishal") -> 19
B23: =Dept_Payroll_Summary!B7 -> Education & Skill Development | C23: =Dept_Payroll_Summary!C7 -> 13 | F23: Female | G23: =COUNTIFS(Employee_Master[Employment Status],"Active",Employee_Master[Gender],"Female") -> 51 | I23: Contractual | J23: =COUNTIFS(Employee_Master[Employment Status],"Active",Employee_Master[Employment Type],"Contractual") -> 41 | L23: Chattogram | M23: =COUNTIFS(Employee_Master[Employment Status],"Active",Employee_Master[Region/Division],"Chattogram") -> 23
B24: =Dept_Payroll_Summary!B8 -> Finance & Accounts | C24: =Dept_Payroll_Summary!C8 -> 14 | I24: Probationary | J24: =COUNTIFS(Employee_Master[Employment Status],"Active",Employee_Master[Employment Type],"Probationary") -> 9 | L24: Dhaka | M24: =COUNTIFS(Employee_Master[Employment Status],"Active",Employee_Master[Region/Division],"Dhaka") -> 10
B25: =Dept_Payroll_Summary!B9 -> Financial Impact Choices (Microfinance) | C25: =Dept_Payroll_Summary!C9 -> 14 | L25: Khulna | M25: =COUNTIFS(Employee_Master[Employment Status],"Active",Employee_Master[Region/Division],"Khulna") -> 19
B26: =Dept_Payroll_Summary!B10 -> Health & Nutrition | C26: =Dept_Payroll_Summary!C10 -> 15 | L26: Mymensingh | M26: =COUNTIFS(Employee_Master[Employment Status],"Active",Employee_Master[Region/Division],"Mymensingh") -> 27
B27: =Dept_Payroll_Summary!B11 -> Human Resources & Admin | C27: =Dept_Payroll_Summary!C11 -> 18 | L27: Rajshahi | M27: =COUNTIFS(Employee_Master[Employment Status],"Active",Employee_Master[Region/Division],"Rajshahi") -> 10
B28: =Dept_Payroll_Summary!B12 -> IT & MIS | C28: =Dept_Payroll_Summary!C12 -> 12 | L28: Rangpur | M28: =COUNTIFS(Employee_Master[Employment Status],"Active",Employee_Master[Region/Division],"Rangpur") -> 13
B29: =Dept_Payroll_Summary!B13 -> Market Connect | C29: =Dept_Payroll_Summary!C13 -> 11 | L29: Sylhet | M29: =COUNTIFS(Employee_Master[Employment Status],"Active",Employee_Master[Region/Division],"Sylhet") -> 22
B30: =Dept_Payroll_Summary!B14 -> Monitoring, Evaluation & Learning | C30: =Dept_Payroll_Summary!C14 -> 12
B31: =Dept_Payroll_Summary!B15 -> Padakhep Institute of Development & Management | C31: =Dept_Payroll_Summary!C15 -> 15
B32: =Dept_Payroll_Summary!B16 -> Padakhep Printing & Packaging | C32: =Dept_Payroll_Summary!C16 -> 8
B33: =Dept_Payroll_Summary!B17 -> Social Development | C33: =Dept_Payroll_Summary!C17 -> 9
B36: Separations by Reason (Attrition sheet) | F36: New Hires by Month (last 12 months)
B37: Reason | C37: Count | F37: Month | G37: New Hires
B38: Better Opportunity | C38: =COUNTIF(Attrition[Reason for Leaving],B38) -> 4 | F38: =TEXT(EDATE(TODAY(),-11),"mmm-yy") -> Oct-25 | G38: =SUMPRODUCT((TEXT(Employee_Master[Joining Date],"mmm-yy")=F38)*1) -> 1
B39: Contract Ended | C39: =COUNTIF(Attrition[Reason for Leaving],B39) -> 2 | F39: =TEXT(EDATE(TODAY(),-10),"mmm-yy") -> Nov-25 | G39: =SUMPRODUCT((TEXT(Employee_Master[Joining Date],"mmm-yy")=F39)*1) -> 1
B40: Health Issue | C40: =COUNTIF(Attrition[Reason for Leaving],B40) -> 4 | F40: =TEXT(EDATE(TODAY(),-9),"mmm-yy") -> Dec-25 | G40: =SUMPRODUCT((TEXT(Employee_Master[Joining Date],"mmm-yy")=F40)*1) -> 0
B41: Higher Studies | C41: =COUNTIF(Attrition[Reason for Leaving],B41) -> 3 | F41: =TEXT(EDATE(TODAY(),-8),"mmm-yy") -> Jan-26 | G41: =SUMPRODUCT((TEXT(Employee_Master[Joining Date],"mmm-yy")=F41)*1) -> 2
B42: Performance Issue | C42: =COUNTIF(Attrition[Reason for Leaving],B42) -> 6 | F42: =TEXT(EDATE(TODAY(),-7),"mmm-yy") -> Feb-26 | G42: =SUMPRODUCT((TEXT(Employee_Master[Joining Date],"mmm-yy")=F42)*1) -> 2
B43: Personal/Family Reason | C43: =COUNTIF(Attrition[Reason for Leaving],B43) -> 4 | F43: =TEXT(EDATE(TODAY(),-6),"mmm-yy") -> Mar-26 | G43: =SUMPRODUCT((TEXT(Employee_Master[Joining Date],"mmm-yy")=F43)*1) -> 1
B44: Relocation | C44: =COUNTIF(Attrition[Reason for Leaving],B44) -> 4 | F44: =TEXT(EDATE(TODAY(),-5),"mmm-yy") -> Apr-26 | G44: =SUMPRODUCT((TEXT(Employee_Master[Joining Date],"mmm-yy")=F44)*1) -> 3
B45: Retirement | C45: =COUNTIF(Attrition[Reason for Leaving],B45) -> 1 | F45: =TEXT(EDATE(TODAY(),-4),"mmm-yy") -> May-26 | G45: =SUMPRODUCT((TEXT(Employee_Master[Joining Date],"mmm-yy")=F45)*1) -> 1
F46: =TEXT(EDATE(TODAY(),-3),"mmm-yy") -> Jun-26 | G46: =SUMPRODUCT((TEXT(Employee_Master[Joining Date],"mmm-yy")=F46)*1) -> 0
F47: =TEXT(EDATE(TODAY(),-2),"mmm-yy") -> Jul-26 | G47: =SUMPRODUCT((TEXT(Employee_Master[Joining Date],"mmm-yy")=F47)*1) -> 0
F48: =TEXT(EDATE(TODAY(),-1),"mmm-yy") -> Aug-26 | G48: =SUMPRODUCT((TEXT(Employee_Master[Joining Date],"mmm-yy")=F48)*1) -> 0
F49: =TEXT(EDATE(TODAY(),0),"mmm-yy") -> Sep-26 | G49: =SUMPRODUCT((TEXT(Employee_Master[Joining Date],"mmm-yy")=F49)*1) -> 0

Sheet Employee_Master
A1: EmpID | B1: Name | C1: Gender | D1: Date of Birth | E1: Age | F1: Joining Date | G1: Tenure (Years) | H1: Department | I1: Designation | J1: Job Level | K1: Region/Division | L1: Branch/Office | M1: Employment Type | N1: Employment Status | O1: Education Level | P1: Marital Status | Q1: Monthly Gross Salary (BDT)
A2: PDK-1001 | B2: Md. Rafiqul Uddin | C2: Male | D2: 34512 | E2: =DATEDIF(D2,TODAY(),"Y") -> 32 | F2: 41942 | G2: =DATEDIF(F2,TODAY(),"Y") -> 11 | H2: Market Connect | I2: Manager | J2: Mid Management | K2: Khulna | L2: Khulna Sadar Branch | M2: Contractual | N2: Active | O2: Master's | P2: Married | Q2: 75247
A3: PDK-1002 | B3: Md. Nazrul Uddin | C3: Male | D3: 36276 | E3: =DATEDIF(D3,TODAY(),"Y") -> 27 | F3: 44969 | G3: =DATEDIF(F3,TODAY(),"Y") -> 3 | H3: Padakhep Institute of Development & Management | I3: Accounts Officer | J3: Officer | K3: Rangpur | L3: Rangpur Sadar Branch | M3: Contractual | N3: Active | O3: SSC | P3: Married | Q3: 31349
A4: PDK-1003 | B4: Md. Sohel Molla | C4: Male | D4: 35137 | E4: =DATEDIF(D4,TODAY(),"Y") -> 30 | F4: 43419 | G4: =DATEDIF(F4,TODAY(),"Y") -> 7 | H4: Education & Skill Development | I4: Assistant | J4: Support Staff | K4: Barishal | L4: Barishal Sadar Branch | M4: Probationary | N4: Resigned | O4: Bachelor's | P4: Single | Q4: 15139
A5: PDK-1004 | B5: Md. Delwar Miah | C5: Male | D5: 27502 | E5: =DATEDIF(D5,TODAY(),"Y") -> 51 | F5: 41385 | G5: =DATEDIF(F5,TODAY(),"Y") -> 13 | H5: Market Connect | I5: Guard | J5: Support Staff | K5: Chattogram | L5: Chattogram Sadar Branch | M5: Permanent | N5: Active | O5: Bachelor's | P5: Single | Q5: 15169
A6: PDK-1005 | B6: Md. Habibur Sarker | C6: Male | D6: 36054 | E6: =DATEDIF(D6,TODAY(),"Y") -> 27 | F6: 46127 | G6: =DATEDIF(F6,TODAY(),"Y") -> 0 | H6: Padakhep Printing & Packaging | I6: Accounts Officer | J6: Officer | K6: Khulna | L6: Khulna Sadar Branch | M6: Probationary | N6: Active | O6: Bachelor's | P6: Married | Q6: 41145
A7: PDK-1006 | B7: Md. Rezaul Ahmed | C7: Male | D7: 37077 | E7: =DATEDIF(D7,TODAY(),"Y") -> 25 | F7: 46131 | G7: =DATEDIF(F7,TODAY(),"Y") -> 0 | H7: Padakhep Institute of Development & Management | I7: Guard | J7: Support Staff | K7: Mymensingh | L7: Jamalpur Branch | M7: Permanent | N7: Resigned | O7: HSC | P7: Single | Q7: 16266
A8: PDK-1007 | B8: Md. Kamal Miah | C8: Male | D8: 33507 | E8: =DATEDIF(D8,TODAY(),"Y") -> 34 | F8: 43073 | G8: =DATEDIF(F8,TODAY(),"Y") -> 8 | H8: Health & Nutrition | I8: HR Officer | J8: Officer | K8: Chattogram | L8: Chattogram Sadar Branch | M8: Permanent | N8: Active | O8: Bachelor's | P8: Single | Q8: 51616
A9: PDK-1008 | B9: Shahida Miah | C9: Female | D9: 33039 | E9: =DATEDIF(D9,TODAY(),"Y") -> 36 | F9: 44594 | G9: =DATEDIF(F9,TODAY(),"Y") -> 4 | H9: Padakhep Institute of Development & Management | I9: Field Officer | J9: Officer | K9: Sylhet | L9: Sylhet Sadar Branch | M9: Permanent | N9: Active | O9: Master's | P9: Single | Q9: 37779
A10: PDK-1009 | B10: Md. Anwar Khatun | C10: Male | D10: 28761 | E10: =DATEDIF(D10,TODAY(),"Y") -> 47 | F10: 38827 | G10: =DATEDIF(F10,TODAY(),"Y") -> 20 | H10: Financial Impact Choices (Microfinance) | I10: Program Officer | J10: Officer | K10: Dhaka | L10: Savar Branch | M10: Probationary | N10: Active | O10: Master's | P10: Single | Q10: 30806
A11: PDK-1010 | B11: Shirin Hossain | C11: Female | D11: 33673 | E11: =DATEDIF(D11,TODAY(),"Y") -> 34 | F11: 44540 | G11: =DATEDIF(F11,TODAY(),"Y") -> 4 | H11: Padakhep Institute of Development & Management | I11: MIS Officer | J11: Officer | K11: Mymensingh | L11: Netrokona Branch | M11: Contractual | N11: Active | O11: Bachelor's | P11: Married | Q11: 38214
A12: PDK-1011 | B12: Parvin Chowdhury | C12: Female | D12: 34479 | E12: =DATEDIF(D12,TODAY(),"Y") -> 32 | F12: 41808 | G12: =DATEDIF(F12,TODAY(),"Y") -> 12 | H12: Monitoring, Evaluation & Learning | I12: Program Officer | J12: Officer | K12: Mymensingh | L12: Mymensingh Sadar Branch | M12: Permanent | N12: Active | O12: Bachelor's | P12: Married | Q12: 35501
A13: PDK-1012 | B13: Nasima Rahman | C13: Female | D13: 28819 | E13: =DATEDIF(D13,TODAY(),"Y") -> 47 | F13: 44780 | G13: =DATEDIF(F13,TODAY(),"Y") -> 4 | H13: Monitoring, Evaluation & Learning | I13: Field Officer | J13: Officer | K13: Khulna | L13: Jashore Branch | M13: Permanent | N13: Active | O13: Bachelor's | P13: Single | Q13: 31090
... A161: PDK-1160 | B161: Md. Alamgir Uddin | C161: Male | D161: 35454 | E161: =DATEDIF(D161,TODAY(),"Y") -> 29 | F161: 45527 | G161: =DATEDIF(F161,TODAY(),"Y") -> 2 | H161: Padakhep Printing & Packaging | I161: Manager | J161: Mid Management | K161: Mymensingh | L161: Jamalpur Branch | M161: Contractual | N161: Active | O161: HSC | P161: Single | Q161: 75985

Sheet Dept_Payroll_Summary
B2: Department-wise Headcount & Payroll Summary
B3: Auto-calculated from Employee_Master (active employees only). Do not overwrite formula cells.
B5: Department | C5: Active Headcount | D5: Male | E5: Female | F5: % Female | G5: Avg. Age | H5: Avg. Tenure (Yrs) | I5: Avg. Monthly Salary (BDT) | J5: Total Monthly Payroll (BDT)
B6: Agriculture & Climate Adaptation | C6: =COUNTIFS(Employee_Master[Department],B6,Employee_Master[Employment Status],"Active") -> 2 | D6: =COUNTIFS(Employee_Master[Department],B6,Employee_Master[Employment Status],"Active",Employee_Master[Gender],"Male") -> 2 | E6: =COUNTIFS(Employee_Master[Department],B6,Employee_Master[Employment Status],"Active",Employee_Master[Gender],"Female") -> 0 | F6: =IFERROR(E6/C6,0) -> 0 | G6: =IFERROR(AVERAGEIFS(Employee_Master[Age],Employee_Master[Department],B6,Employee_Master[Employment Status],"Active"),0) -> 43 | H6: =IFERROR(AVERAGEIFS(Employee_Master[Tenure (Years)],Employee_Master[Department],B6,Employee_Master[Employment Status],"Active"),0) -> 7 | I6: =IFERROR(AVERAGEIFS(Employee_Master[Monthly Gross Salary (BDT)],Employee_Master[Department],B6,Employee_Master[Employment Status],"Active"),0) -> 31508.5 | J6: =IFERROR(SUMIFS(Employee_Master[Monthly Gross Salary (BDT)],Employee_Master[Department],B6,Employee_Master[Employment Status],"Active"),0) -> 63017
B7: Education & Skill Development | C7: =COUNTIFS(Employee_Master[Department],B7,Employee_Master[Employment Status],"Active") -> 13 | D7: =COUNTIFS(Employee_Master[Department],B7,Employee_Master[Employment Status],"Active",Employee_Master[Gender],"Male") -> 8 | E7: =COUNTIFS(Employee_Master[Department],B7,Employee_Master[Employment Status],"Active",Employee_Master[Gender],"Female") -> 5 | F7: =IFERROR(E7/C7,0) -> 0.38461538 | G7: =IFERROR(AVERAGEIFS(Employee_Master[Age],Employee_Master[Department],B7,Employee_Master[Employment Status],"Active"),0) -> 39 | H7: =IFERROR(AVERAGEIFS(Employee_Master[Tenure (Years)],Employee_Master[Department],B7,Employee_Master[Employment Status],"Active"),0) -> 8.9230769 | I7: =IFERROR(AVERAGEIFS(Employee_Master[Monthly Gross Salary (BDT)],Employee_Master[Department],B7,Employee_Master[Employment Status],"Active"),0) -> 35315.154 | J7: =IFERROR(SUMIFS(Employee_Master[Monthly Gross Salary (BDT)],Employee_Master[Department],B7,Employee_Master[Employment Status],"Active"),0) -> 459097
B8: Finance & Accounts | C8: =COUNTIFS(Employee_Master[Department],B8,Employee_Master[Employment Status],"Active") -> 14 | D8: =COUNTIFS(Employee_Master[Department],B8,Employee_Master[Employment Status],"Active",Employee_Master[Gender],"Male") -> 8 | E8: =COUNTIFS(Employee_Master[Department],B8,Employee_Master[Employment Status],"Active",Employee_Master[Gender],"Female") -> 6 | F8: =IFERROR(E8/C8,0) -> 0.42857143 | G8: =IFERROR(AVERAGEIFS(Employee_Master[Age],Employee_Master[Department],B8,Employee_Master[Employment Status],"Active"),0) -> 42.714286 | H8: =IFERROR(AVERAGEIFS(Employee_Master[Tenure (Years)],Employee_Master[Department],B8,Employee_Master[Employment Status],"Active"),0) -> 9.5714286 | I8: =IFERROR(AVERAGEIFS(Employee_Master[Monthly Gross Salary (BDT)],Employee_Master[Department],B8,Employee_Master[Employment Status],"Active"),0) -> 46759.357 | J8: =IFERROR(SUMIFS(Employee_Master[Monthly Gross Salary (BDT)],Employee_Master[Department],B8,Employee_Master[Employment Status],"Active"),0) -> 654631
B9: Financial Impact Choices (Microfinance) | C9: =COUNTIFS(Employee_Master[Department],B9,Employee_Master[Employment Status],"Active") -> 14 | D9: =COUNTIFS(Employee_Master[Department],B9,Employee_Master[Employment Status],"Active",Employee_Master[Gender],"Male") -> 11 | E9: =COUNTIFS(Employee_Master[Department],B9,Employee_Master[Employment Status],"Active",Employee_Master[Gender],"Female") -> 3 | F9: =IFERROR(E9/C9,0) -> 0.21428571 | G9: =IFERROR(AVERAGEIFS(Employee_Master[Age],Employee_Master[Department],B9,Employee_Master[Employment Status],"Active"),0) -> 40.214286 | H9: =IFERROR(AVERAGEIFS(Employee_Master[Tenure (Years)],Employee_Master[Department],B9,Employee_Master[Employment Status],"Active"),0) -> 7.2857143 | I9: =IFERROR(AVERAGEIFS(Employee_Master[Monthly Gross Salary (BDT)],Employee_Master[Department],B9,Employee_Master[Employment Status],"Active"),0) -> 56226.929 | J9: =IFERROR(SUMIFS(Employee_Master[Monthly Gross Salary (BDT)],Employee_Master[Department],B9,Employee_Master[Employment Status],"Active"),0) -> 787177
B10: Health & Nutrition | C10: =COUNTIFS(Employee_Master[Department],B10,Employee_Master[Employment Status],"Active") -> 15 | D10: =COUNTIFS(Employee_Master[Department],B10,Employee_Master[Employment Status],"Active",Employee_Master[Gender],"Male") -> 9 | E10: =COUNTIFS(Employee_Master[Department],B10,Employee_Master[Employment Status],"Active",Employee_Master[Gender],"Female") -> 6 | F10: =IFERROR(E10/C10,0) -> 0.4 | G10: =IFERROR(AVERAGEIFS(Employee_Master[Age],Employee_Master[Department],B10,Employee_Master[Employment Status],"Active"),0) -> 37.533333 | H10: =IFERROR(AVERAGEIFS(Employee_Master[Tenure (Years)],Employee_Master[Department],B10,Employee_Master[Employment Status],"Active"),0) -> 8.2 | I10: =IFERROR(AVERAGEIFS(Employee_Master[Monthly Gross Salary (BDT)],Employee_Master[Department],B10,Employee_Master[Employment Status],"Active"),0) -> 39156.867 | J10: =IFERROR(SUMIFS(Employee_Master[Monthly Gross Salary (BDT)],Employee_Master[Department],B10,Employee_Master[Employment Status],"Active"),0) -> 587353
B11: Human Resources & Admin | C11: =COUNTIFS(Employee_Master[Department],B11,Employee_Master[Employment Status],"Active") -> 18 | D11: =COUNTIFS(Employee_Master[Department],B11,Employee_Master[Employment Status],"Active",Employee_Master[Gender],"Male") -> 9 | E11: =COUNTIFS(Employee_Master[Department],B11,Employee_Master[Employment Status],"Active",Employee_Master[Gender],"Female") -> 9 | F11: =IFERROR(E11/C11,0) -> 0.5 | G11: =IFERROR(AVERAGEIFS(Employee_Master[Age],Employee_Master[Department],B11,Employee_Master[Employment Status],"Active"),0) -> 40.722222 | H11: =IFERROR(AVERAGEIFS(Employee_Master[Tenure (Years)],Employee_Master[Department],B11,Employee_Master[Employment Status],"Active"),0) -> 10.444444 | I11: =IFERROR(AVERAGEIFS(Employee_Master[Monthly Gross Salary (BDT)],Employee_Master[Department],B11,Employee_Master[Employment Status],"Active"),0) -> 50279.444 | J11: =IFERROR(SUMIFS(Employee_Master[Monthly Gross Salary (BDT)],Employee_Master[Department],B11,Employee_Master[Employment Status],"Active"),0) -> 905030
B12: IT & MIS | C12: =COUNTIFS(Employee_Master[Department],B12,Employee_Master[Employment Status],"Active") -> 12 | D12: =COUNTIFS(Employee_Master[Department],B12,Employee_Master[Employment Status],"Active",Employee_Master[Gender],"Male") -> 7 | E12: =COUNTIFS(Employee_Master[Department],B12,Employee_Master[Employment Status],"Active",Employee_Master[Gender],"Female") -> 5 | F12: =IFERROR(E12/C12,0) -> 0.41666667 | G12: =IFERROR(AVERAGEIFS(Employee_Master[Age],Employee_Master[Department],B12,Employee_Master[Employment Status],"Active"),0) -> 38.25 | H12: =IFERROR(AVERAGEIFS(Employee_Master[Tenure (Years)],Employee_Master[Department],B12,Employee_Master[Employment Status],"Active"),0) -> 6.9166667 | I12: =IFERROR(AVERAGEIFS(Employee_Master[Monthly Gross Salary (BDT)],Employee_Master[Department],B12,Employee_Master[Employment Status],"Active"),0) -> 45508.917 | J12: =IFERROR(SUMIFS(Employee_Master[Monthly Gross Salary (BDT)],Employee_Master[Department],B12,Employee_Master[Employment Status],"Active"),0) -> 546107
B13: Market Connect | C13: =COUNTIFS(Employee_Master[Department],B13,Employee_Master[Employment Status],"Active") -> 11 | D13: =COUNTIFS(Employee_Master[Department],B13,Employee_Master[Employment Status],"Active",Employee_Master[Gender],"Male") -> 9 | E13: =COUNTIFS(Employee_Master[Department],B13,Employee_Master[Employment Status],"Active",Employee_Master[Gender],"Female") -> 2 | F13: =IFERROR(E13/C13,0) -> 0.18181818 | G13: =IFERROR(AVERAGEIFS(Employee_Master[Age],Employee_Master[Department],B13,Employee_Master[Employment Status],"Active"),0) -> 44 | H13: =IFERROR(AVERAGEIFS(Employee_Master[Tenure (Years)],Employee_Master[Department],B13,Employee_Master[Employment Status],"Active"),0) -> 11.454545 | I13: =IFERROR(AVERAGEIFS(Employee_Master[Monthly Gross Salary (BDT)],Employee_Master[Department],B13,Employee_Master[Employment Status],"Active"),0) -> 51229.818 | J13: =IFERROR(SUMIFS(Employee_Master[Monthly Gross Salary (BDT)],Employee_Master[Department],B13,Employee_Master[Employment Status],"Active"),0) -> 563528
B14: Monitoring, Evaluation & Learning | C14: =COUNTIFS(Employee_Master[Department],B14,Employee_Master[Employment Status],"Active") -> 12 | D14: =COUNTIFS(Employee_Master[Department],B14,Employee_Master[Employment Status],"Active",Employee_Master[Gender],"Male") -> 6 | E14: =COUNTIFS(Employee_Master[Department],B14,Employee_Master[Employment Status],"Active",Employee_Master[Gender],"Female") -> 6 | F14: =IFERROR(E14/C14,0) -> 0.5 | G14: =IFERROR(AVERAGEIFS(Employee_Master[Age],Employee_Master[Department],B14,Employee_Master[Employment Status],"Active"),0) -> 38.916667 | H14: =IFERROR(AVERAGEIFS(Employee_Master[Tenure (Years)],Employee_Master[Department],B14,Employee_Master[Employment Status],"Active"),0) -> 8.75 | I14: =IFERROR(AVERAGEIFS(Employee_Master[Monthly Gross Salary (BDT)],Employee_Master[Department],B14,Employee_Master[Employment Status],"Active"),0) -> 47837.25 | J14: =IFERROR(SUMIFS(Employee_Master[Monthly Gross Salary (BDT)],Employee_Master[Department],B14,Employee_Master[Employment Status],"Active"),0) -> 574047
B15: Padakhep Institute of Development & Management | C15: =COUNTIFS(Employee_Master[Department],B15,Employee_Master[Employment Status],"Active") -> 15 | D15: =COUNTIFS(Employee_Master[Department],B15,Employee_Master[Employment Status],"Active",Employee_Master[Gender],"Male") -> 8 | E15: =COUNTIFS(Employee_Master[Department],B15,Employee_Master[Employment Status],"Active",Employee_Master[Gender],"Female") -> 7 | F15: =IFERROR(E15/C15,0) -> 0.46666667 | G15: =IFERROR(AVERAGEIFS(Employee_Master[Age],Employee_Master[Department],B15,Employee_Master[Employment Status],"Active"),0) -> 42.266667 | H15: =IFERROR(AVERAGEIFS(Employee_Master[Tenure (Years)],Employee_Master[Department],B15,Employee_Master[Employment Status],"Active"),0) -> 8.4 | I15: =IFERROR(AVERAGEIFS(Employee_Master[Monthly Gross Salary (BDT)],Employee_Master[Department],B15,Employee_Master[Employment Status],"Active"),0) -> 42257.133 | J15: =IFERROR(SUMIFS(Employee_Master[Monthly Gross Salary (BDT)],Employee_Master[Department],B15,Employee_Master[Employment Status],"Active"),0) -> 633857
B16: Padakhep Printing & Packaging | C16: =COUNTIFS(Employee_Master[Department],B16,Employee_Master[Employment Status],"Active") -> 8 | D16: =COUNTIFS(Employee_Master[Department],B16,Employee_Master[Employment Status],"Active",Employee_Master[Gender],"Male") -> 7 | E16: =COUNTIFS(Employee_Master[Department],B16,Employee_Master[Employment Status],"Active",Employee_Master[Gender],"Female") -> 1 | F16: =IFERROR(E16/C16,0) -> 0.125 | G16: =IFERROR(AVERAGEIFS(Employee_Master[Age],Employee_Master[Department],B16,Employee_Master[Employment Status],"Active"),0) -> 35.25 | H16: =IFERROR(AVERAGEIFS(Employee_Master[Tenure (Years)],Employee_Master[Department],B16,Employee_Master[Employment Status],"Active"),0) -> 4.75 | I16: =IFERROR(AVERAGEIFS(Employee_Master[Monthly Gross Salary (BDT)],Employee_Master[Department],B16,Employee_Master[Employment Status],"Active"),0) -> 53615.375 | J16: =IFERROR(SUMIFS(Employee_Master[Monthly Gross Salary (BDT)],Employee_Master[Department],B16,Employee_Master[Employment Status],"Active"),0) -> 428923
B17: Social Development | C17: =COUNTIFS(Employee_Master[Department],B17,Employee_Master[Employment Status],"Active") -> 9 | D17: =COUNTIFS(Employee_Master[Department],B17,Employee_Master[Employment Status],"Active",Employee_Master[Gender],"Male") -> 8 | E17: =COUNTIFS(Employee_Master[Department],B17,Employee_Master[Employment Status],"Active",Employee_Master[Gender],"Female") -> 1 | F17: =IFERROR(E17/C17,0) -> 0.11111111 | G17: =IFERROR(AVERAGEIFS(Employee_Master[Age],Employee_Master[Department],B17,Employee_Master[Employment Status],"Active"),0) -> 46 | H17: =IFERROR(AVERAGEIFS(Employee_Master[Tenure (Years)],Employee_Master[Department],B17,Employee_Master[Employment Status],"Active"),0) -> 12.666667 | I17: =IFERROR(AVERAGEIFS(Employee_Master[Monthly Gross Salary (BDT)],Employee_Master[Department],B17,Employee_Master[Employment Status],"Active"),0) -> 45652 | J17: =IFERROR(SUMIFS(Employee_Master[Monthly Gross Salary (BDT)],Employee_Master[Department],B17,Employee_Master[Employment Status],"Active"),0) -> 410868
B18: TOTAL | C18: =SUM(C6:C17) -> 143 | D18: =SUM(D6:D17) -> 92 | E18: =SUM(E6:E17) -> 51 | F18: =IFERROR(E18/C18,0) -> 0.35664336 | I18: =IFERROR(AVERAGE(I6:I17),0) -> 45445.562 | J18: =SUM(J6:J17) -> 6613635

Sheet Recruitment
A1: Position | B1: Department | C1: Region | D1: Vacancy Open Date | E1: Position Filled Date | F1: Days to Fill | G1: Applicants | H1: Interviewed | I1: Hired | J1: Source of Hire
A2: Office Support Staff | B2: Monitoring, Evaluation & Learning | C2: Rajshahi | D2: 45996 | E2: 46045 | F2: =E2-D2 -> 49 | G2: 124 | H2: 30 | I2: 1 | J2: Internal Referral
A3: HR Officer | B3: Padakhep Institute of Development & Management | C3: Rangpur | D3: 46063 | E3: 46078 | F3: =E3-D3 -> 15 | G3: 203 | H3: 37 | I3: 1 | J3: NGO Job Portal
A4: MIS Officer | B4: Health & Nutrition | C4: Khulna | D4: 45868 | E4: 45899 | F4: =E4-D4 -> 31 | G4: 207 | H4: 41 | I4: 1 | J4: Internal Referral
A5: Accounts Officer | B5: Education & Skill Development | C5: Sylhet | D5: 45859 | E5: 45902 | F5: =E5-D5 -> 43 | G5: 44 | H5: 5 | I5: 2 | J5: Walk-in
A6: Accounts Officer | B6: Human Resources & Admin | C6: Rangpur | D6: 46259 | E6: Open | F6: — | G6: 104 | H6: 14 | I6: 2 | J6: Walk-in
A7: Coordinator | B7: IT & MIS | C7: Chattogram | D7: 46346 | E7: Open | F7: — | G7: 95 | H7: 9 | I7: 1 | J7: University Career Fair
A8: MIS Officer | B8: Financial Impact Choices (Microfinance) | C8: Rangpur | D8: 46086 | E8: 46138 | F8: =E8-D8 -> 52 | G8: 50 | H8: 8 | I8: 2 | J8: University Career Fair
A9: HR Officer | B9: Padakhep Institute of Development & Management | C9: Rajshahi | D9: 46226 | E9: 46250 | F9: =E9-D9 -> 24 | G9: 140 | H9: 18 | I9: 1 | J9: Walk-in
A10: Guard | B10: Health & Nutrition | C10: Sylhet | D10: 45667 | E10: 45712 | F10: =E10-D10 -> 45 | G10: 49 | H10: 5 | I10: 2 | J10: NGO Job Portal
A11: Field Officer | B11: Padakhep Institute of Development & Management | C11: Mymensingh | D11: 46083 | E11: 46142 | F11: =E11-D11 -> 59 | G11: 128 | H11: 20 | I11: 1 | J11: Newspaper Ad
A12: HR Officer | B12: Health & Nutrition | C12: Barishal | D12: 45888 | E12: 45936 | F12: =E12-D12 -> 48 | G12: 88 | H12: 9 | I12: 2 | J12: Walk-in
A13: Program Officer | B13: Monitoring, Evaluation & Learning | C13: Chattogram | D13: 46244 | E13: 46265 | F13: =E13-D13 -> 21 | G13: 83 | H13: 17 | I13: 1 | J13: University Career Fair
A14: Program Officer | B14: Finance & Accounts | C14: Khulna | D14: 46093 | E14: 46113 | F14: =E14-D14 -> 20 | G14: 203 | H14: 44 | I14: 1 | J14: NGO Job Portal
A15: MIS Officer | B15: Market Connect | C15: Sylhet | D15: 45747 | E15: 45789 | F15: =E15-D15 -> 42 | G15: 45 | H15: 9 | I15: 1 | J15: University Career Fair
A16: Driver | B16: Education & Skill Development | C16: Rangpur | D16: 45827 | E16: 45880 | F16: =E16-D16 -> 53 | G16: 50 | H16: 10 | I16: 1 | J16: Walk-in
A17: Assistant | B17: Market Connect | C17: Rajshahi | D17: 45989 | E17: 46048 | F17: =E17-D17 -> 59 | G17: 89 | H17: 11 | I17: 1 | J17: Internal Referral
A18: Accounts Officer | B18: Human Resources & Admin | C18: Dhaka | D18: 45941 | E18: 46010 | F18: =E18-D18 -> 69 | G18: 182 | H18: 18 | I18: 1 | J18: Internal Referral
A19: Program Officer | B19: Padakhep Institute of Development & Management | C19: Rangpur | D19: 46159 | E19: 46182 | F19: =E19-D19 -> 23 | G19: 162 | H19: 30 | I19: 2 | J19: University Career Fair
... A22: Field Officer | B22: Human Resources & Admin | C22: Khulna | D22: 46164 | E22: 46195 | F22: =E22-D22 -> 31 | G22: 97 | H22: 21 | I22: 1 | J22: Walk-in
A23: Executive Director | B23: Finance & Accounts | C23: Sylhet | D23: 46356 | E23: Open | F23: — | G23: 27 | H23: 3 | I23: 2 | J23: NGO Job Portal
A24: Accounts Officer | B24: Finance & Accounts | C24: Dhaka | D24: 46096 | E24: 46122 | F24: =E24-D24 -> 26 | G24: 191 | H24: 44 | I24: 1 | J24: BDJobs
A25: Coordinator | B25: Padakhep Institute of Development & Management | C25: Sylhet | D25: 45914 | E25: 45933 | F25: =E25-D25 -> 19 | G25: 110 | H25: 21 | I25: 1 | J25: University Career Fair
A26: Program Officer | B26: Padakhep Printing & Packaging | C26: Khulna | D26: 46097 | E26: 46152 | F26: =E26-D26 -> 55 | G26: 38 | H26: 7 | I26: 1 | J26: Internal Referral
A27: Guard | B27: IT & MIS | C27: Khulna | D27: 46189 | E27: 46246 | F27: =E27-D27 -> 57 | G27: 128 | H27: 10 | I27: 1 | J27: University Career Fair
A28: Coordinator | B28: Financial Impact Choices (Microfinance) | C28: Mymensingh | D28: 45730 | E28: 45758 | F28: =E28-D28 -> 28 | G28: 113 | H28: 10 | I28: 1 | J28: Newspaper Ad
A29: Field Officer | B29: Financial Impact Choices (Microfinance) | C29: Rangpur | D29: 45794 | E29: 45849 | F29: =E29-D29 -> 55 | G29: 188 | H29: 19 | I29: 1 | J29: NGO Job Portal
A30: Assistant | B30: Education & Skill Development | C30: Khulna | D30: 46301 | E30: Open | F30: — | G30: 53 | H30: 12 | I30: 2 | J30: BDJobs
A31: Field Officer | B31: Financial Impact Choices (Microfinance) | C31: Chattogram | D31: 46261 | E31: Open | F31: — | G31: 113 | H31: 15 | I31: 2 | J31: Internal Referral
A32: Assistant | B32: Market Connect | C32: Chattogram | D32: 45912 | E32: 45961 | F32: =E32-D32 -> 49 | G32: 168 | H32: 30 | I32: 1 | J32: University Career Fair
A33: Program Officer | B33: Market Connect | C33: Khulna | D33: 46188 | E33: 46240 | F33: =E33-D33 -> 52 | G33: 145 | H33: 16 | I33: 2 | J33: Internal Referral
A34: Program Officer | B34: Finance & Accounts | C34: Rangpur | D34: 45773 | E34: 45802 | F34: =E34-D34 -> 29 | G34: 142 | H34: 26 | I34: 1 | J34: Newspaper Ad
A35: Assistant | B35: Education & Skill Development | C35: Rajshahi | D35: 46054 | E35: 46123 | F35: =E35-D35 -> 69 | G35: 160 | H35: 24 | I35: 1 | J35: BDJobs
A36: Guard | B36: IT & MIS | C36: Chattogram | D36: 45672 | E36: 45702 | F36: =E36-D36 -> 30 | G36: 70 | H36: 6 | I36: 1 | J36: Walk-in

Sheet Attrition
A1: EmpID | B1: Name | C1: Department | D1: Join Date | E1: Exit Date | F1: Tenure (Months) | G1: Exit Type | H1: Reason for Leaving
A2: PDK-EXT-2000 | B2: Md. Ashraf Miah | C2: Human Resources & Admin | D2: 43648 | E2: 45475 | F2: =ROUND((E2-D2)/30.44,1) -> 60 | G2: Resignation | H2: Relocation
A3: PDK-EXT-2001 | B3: Md. Mizanur Rahman | C3: Monitoring, Evaluation & Learning | D3: 41843 | E3: 42659 | F3: =ROUND((E3-D3)/30.44,1) -> 26.8 | G3: Retirement | H3: Performance Issue
A4: PDK-EXT-2002 | B4: Md. Kamal Begum | C4: Padakhep Printing & Packaging | D4: 43762 | E4: 44919 | F4: =ROUND((E4-D4)/30.44,1) -> 38 | G4: Resignation | H4: Personal/Family Reason
A5: PDK-EXT-2003 | B5: Md. Faruk Rahman | C5: Finance & Accounts | D5: 45194 | E5: 46256 | F5: =ROUND((E5-D5)/30.44,1) -> 34.9 | G5: Retirement | H5: Relocation
A6: PDK-EXT-2004 | B6: Md. Anwar Uddin | C6: Health & Nutrition | D6: 41521 | E6: 43734 | F6: =ROUND((E6-D6)/30.44,1) -> 72.7 | G6: Retirement | H6: Contract Ended
A7: PDK-EXT-2005 | B7: Md. Anwar Uddin | C7: Market Connect | D7: 41146 | E7: 41446 | F7: =ROUND((E7-D7)/30.44,1) -> 9.9 | G7: Retirement | H7: Performance Issue
A8: PDK-EXT-2006 | B8: Md. Kamal Begum | C8: Padakhep Printing & Packaging | D8: 44902 | E8: 46251 | F8: =ROUND((E8-D8)/30.44,1) -> 44.3 | G8: Termination | H8: Health Issue
A9: PDK-EXT-2007 | B9: Md. Aminul Chowdhury | C9: IT & MIS | D9: 41546 | E9: 43232 | F9: =ROUND((E9-D9)/30.44,1) -> 55.4 | G9: Contract End | H9: Contract Ended
A10: PDK-EXT-2008 | B10: Rina Ahmed | C10: Padakhep Printing & Packaging | D10: 44347 | E10: 44537 | F10: =ROUND((E10-D10)/30.44,1) -> 6.2 | G10: Resignation | H10: Better Opportunity
A11: PDK-EXT-2009 | B11: Md. Mostafa Khatun | C11: Human Resources & Admin | D11: 41408 | E11: 42321 | F11: =ROUND((E11-D11)/30.44,1) -> 30 | G11: Resignation | H11: Performance Issue
A12: PDK-EXT-2010 | B12: Md. Delwar Talukder | C12: Padakhep Printing & Packaging | D12: 42799 | E12: 44090 | F12: =ROUND((E12-D12)/30.44,1) -> 42.4 | G12: Resignation | H12: Retirement
A13: PDK-EXT-2011 | B13: Md. Aminul Hossain | C13: Agriculture & Climate Adaptation | D13: 44404 | E13: 44772 | F13: =ROUND((E13-D13)/30.44,1) -> 12.1 | G13: Termination | H13: Higher Studies
... A29: PDK-EXT-2027 | B29: Md. Jahangir Khatun | C29: Padakhep Institute of Development & Management | D29: 45342 | E29: 46249 | F29: =ROUND((E29-D29)/30.44,1) -> 29.8 | G29: Retirement | H29: Higher Studies

Sheet Training
A1: EmpID | B1: Name | C1: Department | D1: Training Program | E1: Category | F1: Start Date | G1: End Date | H1: Duration (Hours) | I1: Cost (BDT)
A2: PDK-1006 | B2: Md. Rezaul Ahmed | C2: Padakhep Institute of Development & Management | D2: Gender & Safeguarding Sensitization | E2: Compliance | F2: 45717 | G2: 45722 | H2: 40 | I2: 10174
A3: PDK-1017 | B3: Md. Aminul Mia | C3: Social Development | D3: MIS & Data Reporting Tools | E3: Technical | F3: 46256 | G3: 46258 | H3: 16 | I3: 4115
A4: PDK-1051 | B4: Md. Rezaul Akter | C4: Social Development | D4: Community Health Worker Refresher | E4: Technical | F4: 45911 | G4: 45913 | H4: 16 | I4: 5866
A5: PDK-1114 | B5: Md. Mizanur Rahman | C5: Human Resources & Admin | D5: Communication & Report Writing | E5: Soft Skill | F5: 45715 | G5: 45717 | H5: 16 | I5: 10932
A6: PDK-1033 | B6: Sultana Chowdhury | C6: Health & Nutrition | D6: Climate-Smart Agriculture Practices | E6: Technical | F6: 46021 | G6: 46023 | H6: 16 | I6: 4385
A7: PDK-1024 | B7: Shahida Khatun | C7: Padakhep Institute of Development & Management | D7: Leadership & People Management | E7: Soft Skill | F7: 46264 | G7: 46267 | H7: 24 | I7: 7378
A8: PDK-1085 | B8: Md. Kamal Begum | C8: Finance & Accounts | D8: Project Monitoring & Evaluation Basics | E8: Technical | F8: 45686 | G8: 45689 | H8: 24 | I8: 10800
A9: PDK-1032 | B9: Md. Anwar Ahmed | C9: Human Resources & Admin | D9: Project Monitoring & Evaluation Basics | E9: Technical | F9: 45803 | G9: 45805 | H9: 16 | I9: 9564
A10: PDK-1011 | B10: Parvin Chowdhury | C10: Monitoring, Evaluation & Learning | D10: Communication & Report Writing | E10: Soft Skill | F10: 45974 | G10: 45976 | H10: 16 | I10: 9535
A11: PDK-1119 | B11: Md. Mostafa Sarker | C11: Human Resources & Admin | D11: Microfinance Operations & Risk Management | E11: Technical | F11: 45750 | G11: 45751 | H11: 8 | I11: 5311
A12: PDK-1013 | B12: Parvin Talukder | C12: Human Resources & Admin | D12: Project Monitoring & Evaluation Basics | E12: Technical | F12: 45882 | G12: 45883 | H12: 8 | I12: 10125
A13: PDK-1044 | B13: Md. Yousuf Hossain | C13: Market Connect | D13: Anti-Money Laundering & Compliance | E13: Compliance | F13: 45658 | G13: 45661 | H13: 24 | I13: 11561
... A71: PDK-1095 | B71: Jesmin Rahman | C71: Market Connect | D71: Climate-Smart Agriculture Practices | E71: Technical | F71: 45811 | G71: 45813 | H71: 16 | I71: 10783

Sheet Leave
A1: EmpID | B1: Name | C1: Department | D1: Leave Type | E1: Year | F1: Entitlement (Days) | G1: Leave Taken (Days) | H1: Leave Balance (Days)
A2: PDK-1151 | B2: Md. Shahidul Rahman | C2: Financial Impact Choices (Microfinance) | D2: Earned Leave | E2: 2026 | F2: 20 | G2: 3 | H2: =F2-G2 -> 17
A3: PDK-1150 | B3: Nasrin Miah | C3: IT & MIS | D3: Casual Leave | E3: 2026 | F3: 10 | G3: 3 | H3: =F3-G3 -> 7
A4: PDK-1026 | B4: Md. Kamal Akter | C4: Education & Skill Development | D4: Earned Leave | E4: 2026 | F4: 20 | G4: 15 | H4: =F4-G4 -> 5
A5: PDK-1028 | B5: Rebeka Sarker | C5: Padakhep Institute of Development & Management | D5: Maternity/Paternity Leave | E5: 2026 | F5: 112 | G5: 22 | H5: =F5-G5 -> 90
A6: PDK-1145 | B6: Md. Delwar Ahmed | C6: IT & MIS | D6: Earned Leave | E6: 2026 | F6: 20 | G6: 17 | H6: =F6-G6 -> 3
A7: PDK-1158 | B7: Nasima Miah | C7: Human Resources & Admin | D7: Earned Leave | E7: 2026 | F7: 20 | G7: 11 | H7: =F7-G7 -> 9
A8: PDK-1074 | B8: Md. Shahjahan Khatun | C8: Human Resources & Admin | D8: Sick Leave | E8: 2026 | F8: 14 | G8: 13 | H8: =F8-G8 -> 1
A9: PDK-1138 | B9: Md. Kamal Sheikh | C9: Finance & Accounts | D9: Earned Leave | E9: 2026 | F9: 20 | G9: 2 | H9: =F9-G9 -> 18
A10: PDK-1089 | B10: Md. Faruk Sarker | C10: Education & Skill Development | D10: Earned Leave | E10: 2026 | F10: 20 | G10: 0 | H10: =F10-G10 -> 20
A11: PDK-1106 | B11: Md. Yousuf Mia | C11: Education & Skill Development | D11: Casual Leave | E11: 2026 | F11: 10 | G11: 2 | H11: =F11-G11 -> 8
A12: PDK-1068 | B12: Md. Sohel Ahmed | C12: Finance & Accounts | D12: Sick Leave | E12: 2026 | F12: 14 | G12: 13 | H12: =F12-G12 -> 1
A13: PDK-1099 | B13: Md. Nazrul Sheikh | C13: Health & Nutrition | D13: Sick Leave | E13: 2026 | F13: 14 | G13: 10 | H13: =F13-G13 -> 4
... A91: PDK-1123 | B91: Md. Nazrul Miah | C91: Market Connect | D91: Sick Leave | E91: 2026 | F91: 14 | G91: 1 | H91: =F91-G91 -> 13
